pipu_cli/__init__.py
pipu_cli/cache.py
pipu_cli/cli.py
pipu_cli/config.py
pipu_cli/config_file.py
pipu_cli/output.py
pipu_cli/package_management.py
pipu_cli/pretty.py
pipu_cli/requirements.py
pipu_cli/rollback.py
pipu_cli-0.2.2.dist-info/licenses/LICENSE
pipu_cli-0.2.2.dist-info/METADATA
pipu_cli-0.2.2.dist-info/WHEEL
pipu_cli-0.2.2.dist-info/entry_points.txt
pipu_cli-0.2.2.dist-info/top_level.txt
pipu_cli-0.2.2.dist-info/RECORD
