Metadata-Version: 2.4
Name: pipu-cli
Version: 0.2.2
Summary: A cute Python package updater
Author-email: Scott Arne Johnson <scott.arne.johnson@gmail.com>
License-Expression: MIT
Keywords: pip,pipu,package,updater,package management
Classifier: Development Status :: 5 - Production/Stable
Classifier: Programming Language :: Python :: 3 :: Only
Requires-Python: >=3.10
License-File: LICENSE
Requires-Dist: rich_click<2.0,>=1.7
Requires-Dist: rich<15.0,>=13.0
Requires-Dist: packaging<26.0,>=23.0
Requires-Dist: tomli>=2.0.0; python_version < "3.11"
Provides-Extra: dev
Requires-Dist: invoke; extra == "dev"
Requires-Dist: build; extra == "dev"
Dynamic: license-file
